{"status":200,"update_at":1704867440775,"data":[{"country":"United Arab Emirates","name":"dirham","code":"AED","exchange_rate":"AED/VND","price":6638.667893999999,"price_1":6635.083428,"price_change":-3.5844659999993382,"percent_change":-0.05402292282977061,"priority":0},{"country":"Albania","name":"lek","code":"ALL","exchange_rate":"ALL/VND","price":255.51226369999998,"price_1":255.4619368,"price_change":0.05032689999998752,"percent_change":0.019700351696381374,"priority":0},{"country":"Armenia","name":"dram","code":"AMD","exchange_rate":"AMD/VND","price":60.55842513,"price_1":60.54509607,"price_change":0.013329060000003778,"percent_change":0.022015094310186927,"priority":0},{"country":"Angola","name":"kwanza","code":"AOA","exchange_rate":"AOA/VND","price":29.42173611,"price_1":29.42173611,"price_change":0,"percent_change":0,"priority":0},{"country":"Argentina","name":"peso","code":"ARS","exchange_rate":"ARS/VND","price":29.93983254,"price_1":29.92625277,"price_change":0.013579769999999769,"percent_change":0.04537744870488097,"priority":0},{"country":"Australia","name":"dollar","code":"AUD","exchange_rate":"AUD/VND","price":16336.518820000001,"price_1":16288.1769,"price_change":48.341920000000755,"percent_change":0.29679147210146495,"priority":1},{"country":"Azerbaijan","name":"manat","code":"AZN","exchange_rate":"AZN/VND","price":14342.64695,"price_1":14342.64695,"price_change":0,"percent_change":0,"priority":0},{"country":"Bosnia and Herzegovina","name":"konvertibilna marka","code":"BAM","exchange_rate":"BAM/VND","price":13629.398120000002,"price_1":13626.89735,"price_change":2.500770000002376,"percent_change":0.018351719659812187,"priority":0},{"country":"Barbados","name":"dollar","code":"BBD","exchange_rate":"BBD/VND","price":12082.61864,"price_1":12080.34547,"price_change":2.273170000000391,"percent_change":0.01881709430947583,"priority":0},{"country":"Bulgaria","name":"lev","code":"BGN","exchange_rate":"BGN/VND","price":13627.59869,"price_1":13619.35654,"price_change":8.242150000000038,"percent_change":0.06051791048859667,"priority":0},{"country":"Bermuda","name":"dollar","code":"BMD","exchange_rate":"BMD/VND","price":24382.500000000004,"price_1":24382.5,"price_change":3.637978807091713e-12,"percent_change":1.4920450352062802e-14,"priority":0},{"country":"Bolivia","name":"boliviano","code":"BOB","exchange_rate":"BOB/VND","price":3531.144359,"price_1":3530.381983,"price_change":0.7623759999996764,"percent_change":0.021594717049621775,"priority":0},{"country":"Brazil","name":"real","code":"BRL","exchange_rate":"BRL/VND","price":4969.630665,"price_1":4966.77927,"price_change":2.851394999999684,"percent_change":0.05740933601020856,"priority":0},{"country":"Botswana","name":"pula","code":"BWP","exchange_rate":"BWP/VND","price":1801.010192,"price_1":1800.630089,"price_change":0.3801029999999628,"percent_change":0.021109443984192067,"priority":0},{"country":"Belarus","name":"rouble","code":"BYN","exchange_rate":"BYN/VND","price":7452.15514,"price_1":7450.547494,"price_change":1.6076459999994768,"percent_change":0.02157755522388294,"priority":0},{"country":"Canada","name":"dollar","code":"CAD","exchange_rate":"CAD/VND","price":18215.800010000003,"price_1":18201.98,"price_change":13.820010000003094,"percent_change":0.07592586081296153,"priority":1},{"country":"Congo, Democratic Republic of the","name":"franc","code":"CDF","exchange_rate":"CDF/VND","price":8.932475233,"price_1":8.930713058,"price_change":0.0017621749999996439,"percent_change":0.019731627122664228,"priority":0},{"country":"Switzerland","name":"franc","code":"CHF","exchange_rate":"CHF/VND","price":28596.015440000003,"price_1":28593.63781,"price_change":2.377630000002682,"percent_change":0.008315241368732585,"priority":1},{"country":"Chile","name":"peso","code":"CLP","exchange_rate":"CLP/VND","price":26.576925,"price_1":26.5633,"price_change":0.013624999999997556,"percent_change":0.05129257283544422,"priority":0},{"country":"China, People’s Republic of","name":"yuan","code":"CNY","exchange_rate":"CNY/VND","price":3428.077093,"price_1":3418.102082,"price_change":9.975010999999995,"percent_change":0.29182893783451364,"priority":1},{"country":"Colombia","name":"peso","code":"COP","exchange_rate":"COP/VND","price":6.279464173,"price_1":6.278428478,"price_change":0.00103569499999967,"percent_change":0.016496086618312353,"priority":0},{"country":"Costa Rica","name":"colon","code":"CRC","exchange_rate":"CRC/VND","price":46.95689133,"price_1":46.94719658,"price_change":0.009694749999994201,"percent_change":0.020650327828359117,"priority":0},{"country":"Cabo Verde","name":"escudo","code":"CVE","exchange_rate":"CVE/VND","price":241.74197859999998,"price_1":241.74197859999998,"price_change":0,"percent_change":0,"priority":0},{"country":"Czech Republic","name":"koruna","code":"CZK","exchange_rate":"CZK/VND","price":1083.521726,"price_1":1083.685647,"price_change":-0.16392100000007304,"percent_change":-0.015126249983457891,"priority":0},{"country":"Greenland","name":"Danish krone","code":"DKK","exchange_rate":"DKK/VND","price":3573.023741,"price_1":3572.049809,"price_change":0.973931999999877,"percent_change":0.02726535328667577,"priority":1},{"country":"Dominican Republic","name":"peso","code":"DOP","exchange_rate":"DOP/VND","price":416.1641673,"price_1":416.0782706,"price_change":0.08589669999997795,"percent_change":0.020644360945865255,"priority":0},{"country":"Algeria","name":"dinar","code":"DZD","exchange_rate":"DZD/VND","price":181.22997769999998,"price_1":181.1881474,"price_change":0.041830299999986664,"percent_change":0.023086664663356817,"priority":0},{"country":"Egypt","name":"pound","code":"EGP","exchange_rate":"EGP/VND","price":789.0903598,"price_1":788.7496963,"price_change":0.3406635000000051,"percent_change":0.043190317739334405,"priority":0},{"country":"GermanyAustria\nBelgium\nCyprus\nEstonia\nFinland\nFrance\nGreece\nIreland\nItaly\nKosovo\nLatvia\nLithuania\nLuxembourg\nMalta\nMontenegro\nNetherlands\nPortugal\nSlovak Republic\nSlovenia\nSpain","name":"euro","code":"EUR","exchange_rate":"EUR/VND","price":26646.1713,"price_1":26640,"price_change":6.171300000001793,"percent_change":0.02316554054054727,"priority":4},{"country":"Fiji","name":"dollar","code":"FJD","exchange_rate":"FJD/VND","price":10889.273260000002,"price_1":10883.69074,"price_change":5.58252000000175,"percent_change":0.05129252689517114,"priority":0},{"country":"United Kingdom\nGuernsey, Channel Islands\nJersey, Channel Islands","name":"sterling","code":"GBP","exchange_rate":"GBP/VND","price":30955.046700000003,"price_1":30968.25,"price_change":-13.203299999997398,"percent_change":-0.04263495677023209,"priority":1},{"country":"Georgia","name":"lari","code":"GEL","exchange_rate":"GEL/VND","price":9081.793663,"price_1":9077.137766,"price_change":4.65589700000055,"percent_change":0.05129256732711519,"priority":0},{"country":"Ghana","name":"cedi","code":"GHS","exchange_rate":"GHS/VND","price":2046.499542,"price_1":2046.058409,"price_change":0.4411330000000362,"percent_change":0.021560137191569108,"priority":0},{"country":"Guatemala","name":"quetzal","code":"GTQ","exchange_rate":"GTQ/VND","price":3118.965511,"price_1":3118.251165,"price_change":0.7143459999997503,"percent_change":0.022908545918870853,"priority":0},{"country":"Guyana","name":"dollar","code":"GYD","exchange_rate":"GYD/VND","price":116.77576549999999,"price_1":116.7506018,"price_change":0.025163699999993128,"percent_change":0.021553379264887977,"priority":0},{"country":"Hong Kong SAR","name":"dollar","code":"HKD","exchange_rate":"HKD/VND","price":3118.2657329999997,"price_1":3118.023,"price_change":0.24273299999958908,"percent_change":0.007784836737881314,"priority":1},{"country":"Honduras","name":"lempira","code":"HNL","exchange_rate":"HNL/VND","price":989.0388072,"price_1":988.8707506,"price_change":0.1680565999999999,"percent_change":0.016994799360586923,"priority":0},{"country":"Croatia","name":"kuna","code":"HRK","exchange_rate":"HRK/VND","price":"#N/A (The result for GOOGLEFINANCE is not available.)","price_1":"#N/A (The result for GOOGLEFINANCE is not available.)","price_change":"#N/A (The result for GOOGLEFINANCE is not available.)","percent_change":"#N/A (The result for GOOGLEFINANCE is not available.)","priority":0},{"country":"Hungary","name":"forint","code":"HUF","exchange_rate":"HUF/VND","price":70.2629771,"price_1":70.26126885,"price_change":0.0017082500000071832,"percent_change":0.0024312825941901323,"priority":0},{"country":"Indonesia","name":"rupiah","code":"IDR","exchange_rate":"IDR/VND","price":1.5653906350000002,"price_1":1.567943867,"price_change":-0.0025532319999999054,"percent_change":-0.1628395029781959,"priority":0},{"country":"Israel\nPalestinian territories","name":"shekel","code":"ILS","exchange_rate":"ILS/VND","price":6536.7239309999995,"price_1":6527.824234,"price_change":8.899696999999833,"percent_change":0.136334813576107,"priority":0},{"country":"India","name":"rupee","code":"INR","exchange_rate":"INR/VND","price":293.16713369999997,"price_1":293.0624098,"price_change":0.10472389999995357,"percent_change":0.035734333881790654,"priority":1},{"country":"Iraq","name":"dinar","code":"IQD","exchange_rate":"IQD/VND","price":18.62247573,"price_1":18.61905773,"price_change":0.003417999999999921,"percent_change":0.01835753478809328,"priority":0},{"country":"Iceland","name":"krona","code":"ISK","exchange_rate":"ISK/VND","price":177.2885905,"price_1":177.2363618,"price_change":0.05222870000000057,"percent_change":0.029468388692686746,"priority":0},{"country":"Jamaica","name":"dollar","code":"JMD","exchange_rate":"JMD/VND","price":157.90987199999998,"price_1":157.8758541,"price_change":0.03401789999998073,"percent_change":0.021547246850321698,"priority":0},{"country":"Jordan","name":"dinar","code":"JOD","exchange_rate":"JOD/VND","price":34371.01056,"price_1":34353.38983,"price_change":17.620730000002368,"percent_change":0.05129255100355366,"priority":0},{"country":"Japan","name":"yen","code":"JPY","exchange_rate":"JPY/VND","price":168.2857474,"price_1":168.7122915,"price_change":-0.426544100000001,"percent_change":-0.2528233694223761,"priority":1},{"country":"Kenya","name":"shilling","code":"KES","exchange_rate":"KES/VND","price":154.07582879999998,"price_1":153.9968398,"price_change":0.07898899999997866,"percent_change":0.05129261100589069,"priority":0},{"country":"Kyrgyzstan","name":"som","code":"KGS","exchange_rate":"KGS/VND","price":273.0974835,"price_1":273.0974835,"price_change":0,"percent_change":0,"priority":0},{"country":"Cambodia","name":"riel","code":"KHR","exchange_rate":"KHR/VND","price":5.954145543,"price_1":5.952913514,"price_change":0.001232029000000523,"percent_change":0.02069623550053348,"priority":0},{"country":"Korea, Republic of","name":"won","code":"KRW","exchange_rate":"KRW/VND","price":18.45642115,"price_1":18.45387543,"price_change":0.0025457200000005287,"percent_change":0.013795042725074516,"priority":1},{"country":"Kuwait","name":"dinar","code":"KWD","exchange_rate":"KWD/VND","price":79305.56858,"price_1":79272.63686,"price_change":32.93172000000777,"percent_change":0.04154235471965827,"priority":0},{"country":"Cayman Islands","name":"dollar","code":"KYD","exchange_rate":"KYD/VND","price":29273.922090000004,"price_1":29267.46831,"price_change":6.453780000003462,"percent_change":0.0220510360911482,"priority":0},{"country":"Kazakhstan","name":"tenge","code":"KZT","exchange_rate":"KZT/VND","price":53.62972325,"price_1":53.61792357,"price_change":0.01179967999999576,"percent_change":0.02200696933851025,"priority":0},{"country":"Lao PDR","name":"kip","code":"LAK","exchange_rate":"LAK/VND","price":1.183265657,"price_1":1.183005095,"price_change":0.0002605620000000197,"percent_change":0.022025433457665684,"priority":0},{"country":"Lebanon","name":"pound","code":"LBP","exchange_rate":"LBP/VND","price":1.6223798520000001,"price_1":1.622033082,"price_change":0.0003467700000001628,"percent_change":0.021378725492613767,"priority":0},{"country":"Sri Lanka","name":"rupee","code":"LKR","exchange_rate":"LKR/VND","price":75.58994379,"price_1":75.5733196,"price_change":0.016624190000001704,"percent_change":0.02199743254364296,"priority":0},{"country":"Libya","name":"dinar","code":"LYD","exchange_rate":"LYD/VND","price":5082.161510999999,"price_1":5081.347271,"price_change":0.8142399999996996,"percent_change":0.016024096692754848,"priority":0},{"country":"Morocco","name":"dirham","code":"MAD","exchange_rate":"MAD/VND","price":2451.450685,"price_1":2450.922581,"price_change":0.5281039999999848,"percent_change":0.021547151431625937,"priority":0},{"country":"Moldova","name":"leu","code":"MDL","exchange_rate":"MDL/VND","price":1381.51245,"price_1":1380.8042,"price_change":0.7082499999999072,"percent_change":0.051292572835446706,"priority":0},{"country":"Madagascar","name":"ariary","code":"MGA","exchange_rate":"MGA/VND","price":5.331621306000001,"price_1":5.330496403,"price_change":0.0011249030000008986,"percent_change":0.021103156534686036,"priority":0},{"country":"North Macedonia","name":"denar","code":"MKD","exchange_rate":"MKD/VND","price":433.2767811,"price_1":433.0585555,"price_change":0.21822559999998248,"percent_change":0.05039170736345895,"priority":0},{"country":"Myanmar","name":"kyat","code":"MMK","exchange_rate":"MMK/VND","price":11.61244114,"price_1":11.61015069,"price_change":0.002290450000000277,"percent_change":0.019727995451196655,"priority":0},{"country":"Macau SAR","name":"pataca","code":"MOP","exchange_rate":"MOP/VND","price":3030.8276499999997,"price_1":3030.160926,"price_change":0.6667239999997037,"percent_change":0.0220029238143408,"priority":0},{"country":"Mauritania","name":"ouguiya","code":"MRU","exchange_rate":"MRU/VND","price":614.9432300999999,"price_1":614.6279716,"price_change":0.3152584999999135,"percent_change":0.05129257283543935,"priority":0},{"country":"Mauritius","name":"rupee","code":"MUR","exchange_rate":"MUR/VND","price":549.4340358,"price_1":539.5427831,"price_change":9.891252699999995,"percent_change":1.8332656852842621,"priority":0},{"country":"Maldives","name":"rufiyaa","code":"MVR","exchange_rate":"MVR/VND","price":1582.4676499999998,"price_1":1581.656378,"price_change":0.8112719999999172,"percent_change":0.05129255704869147,"priority":0},{"country":"Malawi","name":"kwacha","code":"MWK","exchange_rate":"MWK/VND","price":14.4851434,"price_1":14.48208939,"price_change":0.0030540099999996073,"percent_change":0.021088186364244,"priority":0},{"country":"Mexico","name":"peso","code":"MXN","exchange_rate":"MXN/VND","price":1436.223878,"price_1":1435.884786,"price_change":0.3390919999999369,"percent_change":0.02361554376131797,"priority":0},{"country":"Malaysia","name":"ringgit","code":"MYR","exchange_rate":"MYR/VND","price":5244.339271,"price_1":5248.198913,"price_change":-3.859642000000349,"percent_change":-0.07354222017842846,"priority":1},{"country":"Mozambique","name":"metical","code":"MZN","exchange_rate":"MZN/VND","price":381.76484869999996,"price_1":381.5691321,"price_change":0.19571659999996882,"percent_change":0.05129256628355258,"priority":0},{"country":"Namibia, Republic of","name":"dollar","code":"NAD","exchange_rate":"NAD/VND","price":1303.2068319999998,"price_1":1302.967638,"price_change":0.2391939999997703,"percent_change":0.018357631688145606,"priority":0},{"country":"Nigeria","name":"naira","code":"NGN","exchange_rate":"NGN/VND","price":27.545666100000002,"price_1":26.64844146,"price_change":0.897224640000001,"percent_change":3.3668934873611964,"priority":0},{"country":"Nicaragua","name":"cordoba oro","code":"NIO","exchange_rate":"NIO/VND","price":666.3203272999999,"price_1":666.2073203,"price_change":0.11300699999992503,"percent_change":0.01696273765785654,"priority":0},{"country":"Norway","name":"kroner","code":"NOK","exchange_rate":"NOK/VND","price":2353.996271,"price_1":2351.07138,"price_change":2.924891000000116,"percent_change":0.12440672898668505,"priority":1},{"country":"New Zealand","name":"dollar","code":"NZD","exchange_rate":"NZD/VND","price":15206.146120000001,"price_1":15199.90018,"price_change":6.245940000000701,"percent_change":0.041091980381681034,"priority":0},{"country":"Oman","name":"rial","code":"OMR","exchange_rate":"OMR/VND","price":63340.61467,"price_1":63319.93738,"price_change":20.67728999999963,"percent_change":0.03265525971055474,"priority":0},{"country":"Panama","name":"balboa","code":"PAB","exchange_rate":"PAB/VND","price":24395.812840000002,"price_1":24390.56828,"price_change":5.244560000002821,"percent_change":0.021502410029139434,"priority":0},{"country":"Peru","name":"nuevo sol","code":"PEN","exchange_rate":"PEN/VND","price":6597.587527,"price_1":6596.135294,"price_change":1.4522329999999783,"percent_change":0.022016422272614144,"priority":0},{"country":"Papua New Guinea","name":"kina","code":"PGK","exchange_rate":"PGK/VND","price":6532.593535,"price_1":6531.125882,"price_change":1.4676529999997001,"percent_change":0.022471669150407905,"priority":0},{"country":"Philippines","name":"peso","code":"PHP","exchange_rate":"PHP/VND","price":432.7320761,"price_1":434.1939538,"price_change":-1.4618777000000023,"percent_change":-0.3366877146044686,"priority":0},{"country":"Pakistan","name":"rupee","code":"PKR","exchange_rate":"PKR/VND","price":86.67693474000001,"price_1":86.6614259,"price_change":0.015508840000009627,"percent_change":0.017895897556434767,"priority":0},{"country":"Poland","name":"zloty","code":"PLN","exchange_rate":"PLN/VND","price":6127.809899999999,"price_1":6126.647244,"price_change":1.1626559999995152,"percent_change":0.018977035133500422,"priority":0},{"country":"Paraguay","name":"guarani","code":"PYG","exchange_rate":"PYG/VND","price":3.3554269960000003,"price_1":3.354762015,"price_change":0.000664981000000342,"percent_change":0.019822002187548378,"priority":0},{"country":"Qatar","name":"riyal","code":"QAR","exchange_rate":"QAR/VND","price":6695.731965999999,"price_1":6692.299314,"price_change":3.432651999999507,"percent_change":0.05129256536417234,"priority":0},{"country":"Romania","name":"leu","code":"RON","exchange_rate":"RON/VND","price":5359.858679999999,"price_1":5357.581221,"price_change":2.2774589999989985,"percent_change":0.04250908956960073,"priority":0},{"country":"Serbia","name":"dinar","code":"RSD","exchange_rate":"RSD/VND","price":227.28543829999998,"price_1":227.2574878,"price_change":0.027950499999974454,"percent_change":0.012299044696196124,"priority":0},{"country":"Russian Federation","name":"ruble","code":"RUB","exchange_rate":"RUB/VND","price":272.1087,"price_1":271.9692,"price_change":0.13949999999999818,"percent_change":0.05129257283545275,"priority":1},{"country":"Rwanda","name":"franc","code":"RWF","exchange_rate":"RWF/VND","price":19.28557732,"price_1":19.28159761,"price_change":0.003979710000002967,"percent_change":0.020639939078175625,"priority":0},{"country":"Saudi Arabia","name":"riyal","code":"SAR","exchange_rate":"SAR/VND","price":6501.871585,"price_1":6498.746194,"price_change":3.1253909999995813,"percent_change":0.04809221512428219,"priority":1},{"country":"Sweden","name":"krona","code":"SEK","exchange_rate":"SEK/VND","price":2380.487857,"price_1":2377.231112,"price_change":3.2567450000001372,"percent_change":0.13699740776403474,"priority":1},{"country":"Singapore","name":"dollar","code":"SGD","exchange_rate":"SGD/VND","price":18297.281450000002,"price_1":18309.19805,"price_change":-11.916599999996834,"percent_change":-0.06508531923383086,"priority":1},{"country":"Swaziland","name":"lilangeni","code":"SZL","exchange_rate":"SZL/VND","price":1303.4235919999999,"price_1":1303.166497,"price_change":0.2570949999999357,"percent_change":0.01972848447161512,"priority":0},{"country":"Thailand","name":"baht","code":"THB","exchange_rate":"THB/VND","price":693.8969347999999,"price_1":697.6811753,"price_change":-3.78424050000001,"percent_change":-0.5424025520500539,"priority":1},{"country":"Tajikistan","name":"somoni","code":"TJS","exchange_rate":"TJS/VND","price":2226.093722,"price_1":2225.603653,"price_change":0.4900689999999486,"percent_change":0.022019599012580725,"priority":0},{"country":"Turkmenistan","name":"manat","code":"TMT","exchange_rate":"TMT/VND","price":6959.289723,"price_1":6955.721955,"price_change":3.5677679999998873,"percent_change":0.05129256205296215,"priority":0},{"country":"Tunisia","name":"dinar","code":"TND","exchange_rate":"TND/VND","price":7880.577609,"price_1":7876.537531,"price_change":4.040077999999994,"percent_change":0.05129256331350291,"priority":0},{"country":"Turkey","name":"lira","code":"TRY","exchange_rate":"TRY/VND","price":813.5338161,"price_1":813.231774,"price_change":0.3020420999999942,"percent_change":0.03714096148928807,"priority":0},{"country":"Trinidad And Tobago","name":"dollar","code":"TTD","exchange_rate":"TTD/VND","price":3593.878093,"price_1":3593.054312,"price_change":0.8237809999995989,"percent_change":0.022927040018525576,"priority":0},{"country":"Taiwan","name":"dollar","code":"TWD","exchange_rate":"TWD/VND","price":783.0715397,"price_1":784.2066166,"price_change":-1.1350768999999445,"percent_change":-0.1447420712823331,"priority":0},{"country":"Tanzania","name":"shilling","code":"TZS","exchange_rate":"TZS/VND","price":9.698561192000001,"price_1":9.689860734,"price_change":0.008700458000001632,"percent_change":0.08978929871998335,"priority":0},{"country":"Ukraine","name":"hryvnia","code":"UAH","exchange_rate":"UAH/VND","price":639.0989728,"price_1":638.9640973,"price_change":0.13487549999990733,"percent_change":0.02110846299030506,"priority":0},{"country":"Uganda","name":"shilling","code":"UGX","exchange_rate":"UGX/VND","price":6.417593474,"price_1":6.416270072,"price_change":0.0013234020000005842,"percent_change":0.020625721566425115,"priority":0},{"country":"United States\nEcuador\nEl Salvador\nPuerto Rico\nTimor-Leste","name":"dollar","code":"USD","exchange_rate":"USD/VND","price":24382.5,"price_1":24370,"price_change":12.5,"percent_change":0.05129257283545342,"priority":5},{"country":"Uruguay","name":"peso","code":"UYU","exchange_rate":"UYU/VND","price":619.6812375,"price_1":619.36355,"price_change":0.31768749999991996,"percent_change":0.0512925728354405,"priority":0},{"country":"Uzbekistan, Republic of","name":"soum","code":"UZS","exchange_rate":"UZS/VND","price":1.9680920050000001,"price_1":1.967733717,"price_change":0.00035828800000015093,"percent_change":0.018208154736830733,"priority":0},{"country":"Cameroon, Republic of\nChad\nCongo, Republic of\nEquatorial Guinea\nGabon","name":"CFA franc BEAC","code":"XAF","exchange_rate":"XAF/VND","price":40.63594764,"price_1":40.62737322,"price_change":0.008574419999995087,"percent_change":0.021105031707474704,"priority":0},{"country":"Saint Lucia","name":"dollar","code":"XCD","exchange_rate":"XCD/VND","price":9022.034593999999,"price_1":9022.034594,"price_change":-1.8189894035458565e-12,"percent_change":-2.0161631886842402e-14,"priority":0},{"country":"Ivory Coast (Cote d'Ivoire)\nSenegal","name":"CFA franc BCEAO","code":"XOF","exchange_rate":"XOF/VND","price":40.63538685,"price_1":40.62812869,"price_change":0.007258160000006342,"percent_change":0.017864864157016488,"priority":0},{"country":"South Africa","name":"rand","code":"ZAR","exchange_rate":"ZAR/VND","price":1303.1227119999999,"price_1":1308.555,"price_change":-5.432288000000199,"percent_change":-0.4151363909044861,"priority":0},{"country":"Zambia","name":"kwacha","code":"ZMW","exchange_rate":"ZMW/VND","price":938.7269814,"price_1":938.5418266,"price_change":0.18515479999996387,"percent_change":0.019727922054439833,"priority":0},{"country":"GLOBAL","name":"crypto","code":"BTC","exchange_rate":"BTC/VND","price":1121002505,"price_1":1123147501,"price_change":-2144996,"percent_change":-0.1909807926465751,"priority":0},{"country":"GLOBAL","name":"crypto","code":"ETH","exchange_rate":"ETH/VND","price":58034007.370000005,"price_1":57145700.4,"price_change":888306.9700000063,"percent_change":1.554459852241143,"priority":0}]}