{"status":200,"update_at":1692665659888,"data":[{"country":"United Arab Emirates","name":"dirham","code":"AED","exchange_rate":"AED/VND","price":6485.161978,"price_1":6485.16174,"price_change":-0.00023800000053597614,"percent_change":-0.0000036699161883351295,"priority":0},{"country":"Albania","name":"lek","code":"ALL","exchange_rate":"ALL/VND","price":244.88536879999998,"price_1":244.8853688,"price_change":-2.842170943040401e-14,"percent_change":-1.1606128030301501e-14,"priority":0},{"country":"Armenia","name":"dram","code":"AMD","exchange_rate":"AMD/VND","price":61.72903454,"price_1":61.72903454,"price_change":0,"percent_change":0,"priority":0},{"country":"Angola","name":"kwanza","code":"AOA","exchange_rate":"AOA/VND","price":28.78549814,"price_1":28.78549814,"price_change":0,"percent_change":0,"priority":0},{"country":"Argentina","name":"peso","code":"ARS","exchange_rate":"ARS/VND","price":68.09214022,"price_1":68.08120446,"price_change":0.010935760000009509,"percent_change":0.016062818051984725,"priority":0},{"country":"Australia","name":"dollar","code":"AUD","exchange_rate":"AUD/VND","price":15270.6447,"price_1":15276.4806,"price_change":-5.835900000000038,"percent_change":-0.03820186175603848,"priority":1},{"country":"Azerbaijan","name":"manat","code":"AZN","exchange_rate":"AZN/VND","price":14011.7646,"price_1":14011.7646,"price_change":0,"percent_change":0,"priority":0},{"country":"Bosnia and Herzegovina","name":"konvertibilna marka","code":"BAM","exchange_rate":"BAM/VND","price":13282.756120000002,"price_1":13282.75612,"price_change":1.8189894035458565e-12,"percent_change":1.3694367246621227e-14,"priority":0},{"country":"Barbados","name":"dollar","code":"BBD","exchange_rate":"BBD/VND","price":11810.939760000001,"price_1":11810.93976,"price_change":1.8189894035458565e-12,"percent_change":1.5400886301242608e-14,"priority":0},{"country":"Bulgaria","name":"lev","code":"BGN","exchange_rate":"BGN/VND","price":13273.781460000002,"price_1":13269.86212,"price_change":3.919340000002194,"percent_change":0.02953564976455229,"priority":0},{"country":"Bermuda","name":"dollar","code":"BMD","exchange_rate":"BMD/VND","price":23820.000000000004,"price_1":23820,"price_change":3.637978807091713e-12,"percent_change":1.527279096176202e-14,"priority":0},{"country":"Bolivia","name":"boliviano","code":"BOB","exchange_rate":"BOB/VND","price":3452.080152,"price_1":3452.080152,"price_change":0,"percent_change":0,"priority":0},{"country":"Brazil","name":"real","code":"BRL","exchange_rate":"BRL/VND","price":4782.940234,"price_1":4782.940234,"price_change":0,"percent_change":0,"priority":0},{"country":"Botswana","name":"pula","code":"BWP","exchange_rate":"BWP/VND","price":1755.726942,"price_1":1755.726942,"price_change":0,"percent_change":0,"priority":0},{"country":"Belarus","name":"rouble","code":"BYN","exchange_rate":"BYN/VND","price":9441.33093,"price_1":9441.33093,"price_change":0,"percent_change":0,"priority":0},{"country":"Canada","name":"dollar","code":"CAD","exchange_rate":"CAD/VND","price":17580.112800000003,"price_1":17548.9,"price_change":31.212800000001153,"percent_change":0.17786186028754594,"priority":1},{"country":"Congo, Democratic Republic of the","name":"franc","code":"CDF","exchange_rate":"CDF/VND","price":9.722448853000001,"price_1":9.722448853,"price_change":1.7763568394002505e-15,"percent_change":1.8270673019299355e-14,"priority":0},{"country":"Switzerland","name":"franc","code":"CHF","exchange_rate":"CHF/VND","price":27109.113240000002,"price_1":27113.3532,"price_change":-4.239959999998973,"percent_change":-0.015637903466690993,"priority":1},{"country":"Chile","name":"peso","code":"CLP","exchange_rate":"CLP/VND","price":27.39410763,"price_1":27.39410763,"price_change":0,"percent_change":0,"priority":0},{"country":"China, People’s Republic of","name":"yuan","code":"CNY","exchange_rate":"CNY/VND","price":3305.2632,"price_1":3304.661268,"price_change":0.6019320000000334,"percent_change":0.018214635364559653,"priority":1},{"country":"Colombia","name":"peso","code":"COP","exchange_rate":"COP/VND","price":5.783653212,"price_1":5.78386521,"price_change":-0.00021199800000015756,"percent_change":-0.0036653343793977794,"priority":0},{"country":"Costa Rica","name":"colon","code":"CRC","exchange_rate":"CRC/VND","price":44.7309825,"price_1":44.7309825,"price_change":0,"percent_change":0,"priority":0},{"country":"Cabo Verde","name":"escudo","code":"CVE","exchange_rate":"CVE/VND","price":234.3334971,"price_1":234.3334971,"price_change":0,"percent_change":0,"priority":0},{"country":"Czech Republic","name":"koruna","code":"CZK","exchange_rate":"CZK/VND","price":1080.219611,"price_1":1080.126475,"price_change":0.09313599999995859,"percent_change":0.008622693930352794,"priority":0},{"country":"Greenland","name":"Danish krone","code":"DKK","exchange_rate":"DKK/VND","price":3483.62736,"price_1":3483.62736,"price_change":0,"percent_change":0,"priority":1},{"country":"Dominican Republic","name":"peso","code":"DOP","exchange_rate":"DOP/VND","price":420.10581279999997,"price_1":420.1058128,"price_change":-5.684341886080802e-14,"percent_change":-1.3530738477991375e-14,"priority":0},{"country":"Algeria","name":"dinar","code":"DZD","exchange_rate":"DZD/VND","price":174.7660775,"price_1":174.7805362,"price_change":-0.01445870000000582,"percent_change":-0.008272488638815504,"priority":0},{"country":"Egypt","name":"pound","code":"EGP","exchange_rate":"EGP/VND","price":770.918674,"price_1":770.6966955,"price_change":0.22197849999997743,"percent_change":0.02880231630628257,"priority":0},{"country":"GermanyAustria\nBelgium\nCyprus\nEstonia\nFinland\nFrance\nGreece\nIreland\nItaly\nKosovo\nLatvia\nLithuania\nLuxembourg\nMalta\nMontenegro\nNetherlands\nPortugal\nSlovak Republic\nSlovenia\nSpain","name":"euro","code":"EUR","exchange_rate":"EUR/VND","price":25959.512400000003,"price_1":25958,"price_change":1.5124000000032538,"percent_change":0.005826334848614122,"priority":4},{"country":"Fiji","name":"dollar","code":"FJD","exchange_rate":"FJD/VND","price":10521.30829,"price_1":10523.86179,"price_change":-2.5534999999999854,"percent_change":-0.024263906643342426,"priority":0},{"country":"United Kingdom\nGuernsey, Channel Islands\nJersey, Channel Islands","name":"sterling","code":"GBP","exchange_rate":"GBP/VND","price":30394.320000000003,"price_1":30317.3,"price_change":77.02000000000407,"percent_change":0.2540463695645855,"priority":1},{"country":"Georgia","name":"lari","code":"GEL","exchange_rate":"GEL/VND","price":9127.642968,"price_1":9127.642968,"price_change":0,"percent_change":0,"priority":0},{"country":"Ghana","name":"cedi","code":"GHS","exchange_rate":"GHS/VND","price":2106.1007759999998,"price_1":2106.100776,"price_change":-4.547473508864641e-13,"percent_change":-2.1591908424730767e-14,"priority":0},{"country":"Guatemala","name":"quetzal","code":"GTQ","exchange_rate":"GTQ/VND","price":3037.902756,"price_1":3037.902756,"price_change":0,"percent_change":0,"priority":0},{"country":"Guyana","name":"dollar","code":"GYD","exchange_rate":"GYD/VND","price":114.15377699999999,"price_1":114.153777,"price_change":-1.4210854715202004e-14,"percent_change":-1.2448869488744121e-14,"priority":0},{"country":"Hong Kong SAR","name":"dollar","code":"HKD","exchange_rate":"HKD/VND","price":3039.105666,"price_1":3037.967,"price_change":1.13866599999983,"percent_change":0.03748118396282218,"priority":1},{"country":"Honduras","name":"lempira","code":"HNL","exchange_rate":"HNL/VND","price":967.5119466,"price_1":967.5119466,"price_change":0,"percent_change":0,"priority":0},{"country":"Croatia","name":"kuna","code":"HRK","exchange_rate":"HRK/VND","price":"#N/A (The result for GOOGLEFINANCE is not available.)","price_1":"#N/A (The result for GOOGLEFINANCE is not available.)","price_change":"#N/A (The result for GOOGLEFINANCE is not available.)","percent_change":"#N/A (The result for GOOGLEFINANCE is not available.)","priority":0},{"country":"Hungary","name":"forint","code":"HUF","exchange_rate":"HUF/VND","price":67.77795204,"price_1":67.8042255,"price_change":-0.02627345999999875,"percent_change":-0.03874900097487102,"priority":0},{"country":"Indonesia","name":"rupiah","code":"IDR","exchange_rate":"IDR/VND","price":1.554317908,"price_1":1.554353424,"price_change":-0.000035516000000068715,"percent_change":-0.002284937225452318,"priority":0},{"country":"Israel\nPalestinian territories","name":"shekel","code":"ILS","exchange_rate":"ILS/VND","price":6288.341844,"price_1":6288.341844,"price_change":0,"percent_change":0,"priority":0},{"country":"India","name":"rupee","code":"INR","exchange_rate":"INR/VND","price":286.6024782,"price_1":286.595094,"price_change":0.00738419999998996,"percent_change":0.002576527007817503,"priority":1},{"country":"Iraq","name":"dinar","code":"IQD","exchange_rate":"IQD/VND","price":18.1832059,"price_1":18.1832059,"price_change":0,"percent_change":0,"priority":0},{"country":"Iceland","name":"krona","code":"ISK","exchange_rate":"ISK/VND","price":180.6461398,"price_1":180.6461398,"price_change":0,"percent_change":0,"priority":0},{"country":"Jamaica","name":"dollar","code":"JMD","exchange_rate":"JMD/VND","price":154.1993893,"price_1":154.1993893,"price_change":0,"percent_change":0,"priority":0},{"country":"Jordan","name":"dinar","code":"JOD","exchange_rate":"JOD/VND","price":33653.991720000005,"price_1":33653.99172,"price_change":7.275957614183426e-12,"percent_change":2.161989482471836e-14,"priority":0},{"country":"Japan","name":"yen","code":"JPY","exchange_rate":"JPY/VND","price":162.8729182,"price_1":162.8812552,"price_change":-0.008337000000011585,"percent_change":-0.005118452697196298,"priority":1},{"country":"Kenya","name":"shilling","code":"KES","exchange_rate":"KES/VND","price":164.95844739999998,"price_1":164.9584474,"price_change":-2.842170943040401e-14,"percent_change":-1.7229617445104548e-14,"priority":0},{"country":"Kyrgyzstan","name":"som","code":"KGS","exchange_rate":"KGS/VND","price":269.8538501,"price_1":269.8538501,"price_change":0,"percent_change":0,"priority":0},{"country":"Cambodia","name":"riel","code":"KHR","exchange_rate":"KHR/VND","price":5.7480694660000005,"price_1":5.748069466,"price_change":8.881784197001252e-16,"percent_change":1.5451769067053325e-14,"priority":0},{"country":"Korea, Republic of","name":"won","code":"KRW","exchange_rate":"KRW/VND","price":17.754401350000002,"price_1":17.7663185,"price_change":-0.0119171499999986,"percent_change":-0.06707720566868482,"priority":1},{"country":"Kuwait","name":"dinar","code":"KWD","exchange_rate":"KWD/VND","price":77292.8034,"price_1":77302.9269,"price_change":-10.123500000001513,"percent_change":-0.013095881884391512,"priority":0},{"country":"Cayman Islands","name":"dollar","code":"KYD","exchange_rate":"KYD/VND","price":28617.9435,"price_1":28617.9435,"price_change":0,"percent_change":0,"priority":0},{"country":"Kazakhstan","name":"tenge","code":"KZT","exchange_rate":"KZT/VND","price":52.41652932,"price_1":52.41652932,"price_change":0,"percent_change":0,"priority":0},{"country":"Lao PDR","name":"kip","code":"LAK","exchange_rate":"LAK/VND","price":1.231644256,"price_1":1.231644256,"price_change":0,"percent_change":0,"priority":0},{"country":"Lebanon","name":"pound","code":"LBP","exchange_rate":"LBP/VND","price":1.561199387,"price_1":1.561199387,"price_change":0,"percent_change":0,"priority":0},{"country":"Sri Lanka","name":"rupee","code":"LKR","exchange_rate":"LKR/VND","price":73.34501952000001,"price_1":73.34501952,"price_change":1.4210854715202004e-14,"percent_change":1.9375350648488048e-14,"priority":0},{"country":"Libya","name":"dinar","code":"LYD","exchange_rate":"LYD/VND","price":4931.67684,"price_1":4931.67684,"price_change":0,"percent_change":0,"priority":0},{"country":"Morocco","name":"dirham","code":"MAD","exchange_rate":"MAD/VND","price":2388.867782,"price_1":2388.867782,"price_change":0,"percent_change":0,"priority":0},{"country":"Moldova","name":"leu","code":"MDL","exchange_rate":"MDL/VND","price":1340.4705,"price_1":1340.4705,"price_change":0,"percent_change":0,"priority":0},{"country":"Madagascar","name":"ariary","code":"MGA","exchange_rate":"MGA/VND","price":5.3288589040000005,"price_1":5.328858904,"price_change":8.881784197001252e-16,"percent_change":1.6667328516306412e-14,"priority":0},{"country":"North Macedonia","name":"denar","code":"MKD","exchange_rate":"MKD/VND","price":422.01965459999997,"price_1":422.0846832,"price_change":-0.0650286000000051,"percent_change":-0.015406529208071746,"priority":0},{"country":"Myanmar","name":"kyat","code":"MMK","exchange_rate":"MMK/VND","price":11.35169016,"price_1":11.35169016,"price_change":0,"percent_change":0,"priority":0},{"country":"Macau SAR","name":"pataca","code":"MOP","exchange_rate":"MOP/VND","price":2954.556576,"price_1":2954.556576,"price_change":0,"percent_change":0,"priority":0},{"country":"Mauritania","name":"ouguiya","code":"MRU","exchange_rate":"MRU/VND","price":628.4960356,"price_1":628.4960356,"price_change":0,"percent_change":0,"priority":0},{"country":"Mauritius","name":"rupee","code":"MUR","exchange_rate":"MUR/VND","price":525.5519267999999,"price_1":525.9679908,"price_change":-0.41606400000011945,"percent_change":-0.0791044335924861,"priority":0},{"country":"Maldives","name":"rufiyaa","code":"MVR","exchange_rate":"MVR/VND","price":1553.8822169999999,"price_1":1553.882217,"price_change":-2.2737367544323206e-13,"percent_change":-1.4632619702811877e-14,"priority":0},{"country":"Malawi","name":"kwacha","code":"MWK","exchange_rate":"MWK/VND","price":22.096474830000002,"price_1":22.09647483,"price_change":3.552713678800501e-15,"percent_change":1.6078192137584965e-14,"priority":0},{"country":"Mexico","name":"peso","code":"MXN","exchange_rate":"MXN/VND","price":1399.925696,"price_1":1398.890002,"price_change":1.0356939999999213,"percent_change":0.07403684339148785,"priority":0},{"country":"Malaysia","name":"ringgit","code":"MYR","exchange_rate":"MYR/VND","price":5123.6843819999995,"price_1":5123.684382,"price_change":-9.094947017729282e-13,"percent_change":-1.7750794818042876e-14,"priority":1},{"country":"Mozambique","name":"metical","code":"MZN","exchange_rate":"MZN/VND","price":376.6010839,"price_1":376.6010839,"price_change":0,"percent_change":0,"priority":0},{"country":"Namibia, Republic of","name":"dollar","code":"NAD","exchange_rate":"NAD/VND","price":1253.024707,"price_1":1253.024707,"price_change":0,"percent_change":0,"priority":0},{"country":"Nigeria","name":"naira","code":"NGN","exchange_rate":"NGN/VND","price":31.13725389,"price_1":31.13725389,"price_change":0,"percent_change":0,"priority":0},{"country":"Nicaragua","name":"cordoba oro","code":"NIO","exchange_rate":"NIO/VND","price":651.3535647,"price_1":651.3535647,"price_change":0,"percent_change":0,"priority":0},{"country":"Norway","name":"kroner","code":"NOK","exchange_rate":"NOK/VND","price":2243.16513,"price_1":2242.87929,"price_change":0.2858400000000074,"percent_change":0.012744332754528553,"priority":1},{"country":"New Zealand","name":"dollar","code":"NZD","exchange_rate":"NZD/VND","price":14125.260000000002,"price_1":14123.4735,"price_change":1.786500000001979,"percent_change":0.012649154614847254,"priority":0},{"country":"Oman","name":"rial","code":"OMR","exchange_rate":"OMR/VND","price":61869.496320000006,"price_1":61875.02256,"price_change":-5.526239999991958,"percent_change":-0.008931293713280157,"priority":0},{"country":"Panama","name":"balboa","code":"PAB","exchange_rate":"PAB/VND","price":23847.512100000004,"price_1":23847.5121,"price_change":3.637978807091713e-12,"percent_change":1.5255171238980995e-14,"priority":0},{"country":"Peru","name":"nuevo sol","code":"PEN","exchange_rate":"PEN/VND","price":6404.086558,"price_1":6404.086558,"price_change":0,"percent_change":0,"priority":0},{"country":"Papua New Guinea","name":"kina","code":"PGK","exchange_rate":"PGK/VND","price":6757.44673,"price_1":6757.44673,"price_change":0,"percent_change":0,"priority":0},{"country":"Philippines","name":"peso","code":"PHP","exchange_rate":"PHP/VND","price":423.2799708,"price_1":422.7163896,"price_change":0.5635811999999873,"percent_change":0.1333237162943415,"priority":0},{"country":"Pakistan","name":"rupee","code":"PKR","exchange_rate":"PKR/VND","price":80.36437096,"price_1":80.36437096,"price_change":0,"percent_change":0,"priority":0},{"country":"Poland","name":"zloty","code":"PLN","exchange_rate":"PLN/VND","price":5799.052842,"price_1":5799.345828,"price_change":-0.2929860000003828,"percent_change":-0.005052052570926328,"priority":0},{"country":"Paraguay","name":"guarani","code":"PYG","exchange_rate":"PYG/VND","price":3.276805446,"price_1":3.276805446,"price_change":0,"percent_change":0,"priority":0},{"country":"Qatar","name":"riyal","code":"QAR","exchange_rate":"QAR/VND","price":6542.608434,"price_1":6542.608434,"price_change":0,"percent_change":0,"priority":0},{"country":"Romania","name":"leu","code":"RON","exchange_rate":"RON/VND","price":5256.428478,"price_1":5257.007304,"price_change":-0.5788259999999354,"percent_change":-0.011010561076441971,"priority":0},{"country":"Serbia","name":"dinar","code":"RSD","exchange_rate":"RSD/VND","price":221.3631188,"price_1":221.3548914,"price_change":0.008227399999981344,"percent_change":0.0037168367719121217,"priority":0},{"country":"Russian Federation","name":"ruble","code":"RUB","exchange_rate":"RUB/VND","price":254.7594258,"price_1":254.7594258,"price_change":0,"percent_change":0,"priority":1},{"country":"Rwanda","name":"franc","code":"RWF","exchange_rate":"RWF/VND","price":20.050505,"price_1":20.050505,"price_change":0,"percent_change":0,"priority":0},{"country":"Saudi Arabia","name":"riyal","code":"SAR","exchange_rate":"SAR/VND","price":6350.552060999999,"price_1":6350.736428,"price_change":-0.1843670000007478,"percent_change":-0.0029030806441263284,"priority":1},{"country":"Sweden","name":"krona","code":"SEK","exchange_rate":"SEK/VND","price":2174.210994,"price_1":2174.59926,"price_change":-0.3882659999999305,"percent_change":-0.017854600024095037,"priority":1},{"country":"Singapore","name":"dollar","code":"SGD","exchange_rate":"SGD/VND","price":17552.005200000003,"price_1":17548.9086,"price_change":3.0966000000044005,"percent_change":0.017645541786025374,"priority":1},{"country":"Swaziland","name":"lilangeni","code":"SZL","exchange_rate":"SZL/VND","price":1253.024707,"price_1":1253.024707,"price_change":0,"percent_change":0,"priority":0},{"country":"Thailand","name":"baht","code":"THB","exchange_rate":"THB/VND","price":678.052974,"price_1":676.8969894,"price_change":1.155984599999897,"percent_change":0.1707770337440205,"priority":1},{"country":"Tajikistan","name":"somoni","code":"TJS","exchange_rate":"TJS/VND","price":2170.0963269999997,"price_1":2170.096327,"price_change":-4.547473508864641e-13,"percent_change":-2.0955168912484136e-14,"priority":0},{"country":"Turkmenistan","name":"manat","code":"TMT","exchange_rate":"TMT/VND","price":6798.74013,"price_1":6798.74013,"price_change":0,"percent_change":0,"priority":0},{"country":"Tunisia","name":"dinar","code":"TND","exchange_rate":"TND/VND","price":7665.328404,"price_1":7665.328404,"price_change":0,"percent_change":0,"priority":0},{"country":"Turkey","name":"lira","code":"TRY","exchange_rate":"TRY/VND","price":875.6129573999999,"price_1":875.283765,"price_change":0.32919239999989713,"percent_change":0.037609791608541616,"priority":0},{"country":"Trinidad And Tobago","name":"dollar","code":"TTD","exchange_rate":"TTD/VND","price":3514.848234,"price_1":3514.848234,"price_change":0,"percent_change":0,"priority":0},{"country":"Taiwan","name":"dollar","code":"TWD","exchange_rate":"TWD/VND","price":745.8389771999999,"price_1":746.0373978,"price_change":-0.19842060000007677,"percent_change":-0.02659660233993658,"priority":0},{"country":"Tanzania","name":"shilling","code":"TZS","exchange_rate":"TZS/VND","price":9.508981873,"price_1":9.508981873,"price_change":0,"percent_change":0,"priority":0},{"country":"Ukraine","name":"hryvnia","code":"UAH","exchange_rate":"UAH/VND","price":645.4431558,"price_1":645.4431558,"price_change":0,"percent_change":0,"priority":0},{"country":"Uganda","name":"shilling","code":"UGX","exchange_rate":"UGX/VND","price":6.391368108,"price_1":6.391368108,"price_change":0,"percent_change":0,"priority":0},{"country":"United States\nEcuador\nEl Salvador\nPuerto Rico\nTimor-Leste","name":"dollar","code":"USD","exchange_rate":"USD/VND","price":23820,"price_1":23820,"price_change":0,"percent_change":0,"priority":5},{"country":"Uruguay","name":"peso","code":"UYU","exchange_rate":"UYU/VND","price":629.3244,"price_1":629.3244,"price_change":0,"percent_change":0,"priority":0},{"country":"Uzbekistan, Republic of","name":"soum","code":"UZS","exchange_rate":"UZS/VND","price":1.9645360630000002,"price_1":1.964536063,"price_change":2.220446049250313e-16,"percent_change":1.1302648452579276e-14,"priority":0},{"country":"Cameroon, Republic of\nChad\nCongo, Republic of\nEquatorial Guinea\nGabon","name":"CFA franc BEAC","code":"XAF","exchange_rate":"XAF/VND","price":39.60353694,"price_1":39.60353694,"price_change":0,"percent_change":0,"priority":0},{"country":"Saint Lucia","name":"dollar","code":"XCD","exchange_rate":"XCD/VND","price":8813.897837999999,"price_1":8813.897838,"price_change":-1.8189894035458565e-12,"percent_change":-2.0637740951608433e-14,"priority":0},{"country":"Ivory Coast (Cote d'Ivoire)\nSenegal","name":"CFA franc BCEAO","code":"XOF","exchange_rate":"XOF/VND","price":39.58164874,"price_1":39.58164874,"price_change":0,"percent_change":0,"priority":0},{"country":"South Africa","name":"rand","code":"ZAR","exchange_rate":"ZAR/VND","price":1255.045786,"price_1":1252.973,"price_change":2.072785999999951,"percent_change":0.16542942266113883,"priority":0},{"country":"Zambia","name":"kwacha","code":"ZMW","exchange_rate":"ZMW/VND","price":1220.837646,"price_1":1220.837646,"price_change":0,"percent_change":0,"priority":0},{"country":"GLOBAL","name":"crypto","code":"BTC","exchange_rate":"BTC/VND","price":622023570,"price_1":622014042,"price_change":9528,"percent_change":0.0015317982162209773,"priority":0},{"country":"GLOBAL","name":"crypto","code":"ETH","exchange_rate":"ETH/VND","price":39735571.2,"price_1":39696982.8,"price_change":38588.40000000596,"percent_change":0.0972073877614849,"priority":0}]}